[
 {
  "id": 1,
  "nombre": "oswar",
  "apellido": "baez",
  "correo": "oswar@gmail.com",
  "contraseña": "$2a$10$Mxvsy5YuLMXVTuAqZUHtL.IaghQ4E/FeFUmfrwNfC9xDZT.IFvn1m",
  "imagen": "imagen1646011585371.png",
  "tipeUser": "master"
 },
 {
  "id": 2,
  "nombre": "admin",
  "apellido": "admin",
  "correo": "admin@cacturi.com",
  "contraseña": "$2a$10$B94K2acBKFvYIfwD7GFCOuINHdwKg0MAGX7259DqGK80mOVALpsJe",
  "imagen": "imagen1646151944299.jpg",
  "tipeUser": "comprador"
 },
 {
  "id": 3,
  "nombre": "vanessa",
  "apellido": "barrios",
  "correo": "vane@gmail.com",
  "contraseña": "$2a$10$MzSVUo9LNmSaHkKVOWqIyuDcnGnSjrvVLwAQ788Q072b9yvV2Fjr.",
  "imagen": "imagen1646158033794.jpeg",
  "tipeUser": "comprador"
 }
]